snote/__init__.py
snote/exceptions.py
snote/lib.py
snote/snotebook.py
snotebook-0.2.2.dist-info/METADATA
snotebook-0.2.2.dist-info/RECORD
snotebook-0.2.2.dist-info/WHEEL
snotebook-0.2.2.dist-info/entry_points.txt
snotebook-0.2.2.dist-info/top_level.txt
