Metadata-Version: 2.1
Name: snotebook
Version: 0.2.2
Summary: A rudimentary CLI to write and organize text
Home-page: https://github.com/nicolemon/snote
Author: Nicole A Montano
Author-email: n@nicolemon.com
License: MIT
Keywords: cli commandline terminal notes python
Platform: UNKNOWN
Classifier: Development Status :: 3 - Alpha
Classifier: License :: OSI Approved :: MIT License
Classifier: Programming Language :: Python :: 3.5
Provides-Extra: test
Provides-Extra: test
Requires-Dist: pytest; extra == 'test'
